{
    "images": [
      {
        "id": 1,
        "title": "Brand1",
        "category": "Brand",
        "source": "Brand1.png"
      },
      {
        "id": 2,
        "title": "Brand2",
        "category": "Brand",
        "source": "Brand2.png"
      },
      {
        "id": 3,
        "title": "Brand3",
        "category": "Brand",
        "source": "Brand3.png"
      },
      {
        "id": 4,
        "title": "Brand4",
        "category": "Brand",
        "source": "Brand4.png"
      },
      {
        "id": 5,
        "title": "Design1",
        "category": "Design",
        "source": "Design1.png"
      },
      {
        "id": 6,
        "title": "Design2",
        "category": "Design",
        "source": "Design2.png"
      },
      {
        "id": 7,
        "title": "Design3",
        "category": "Design",
        "source": "Design3.png"
      },
      {
        "id": 8,
        "title": "Design4",
        "category": "Design",
        "source": "Design4.png"
      },
      {
        "id": 9,
        "title": "Design5",
        "category": "Design",
        "source": "Design5.png"
      },
      {
        "id": 10,
        "title": "Design6",
        "category": "Design",
        "source": "Design6.jpg"
      },
      {
        "id": 11,
        "title": "Design7",
        "category": "Design",
        "source": "Design7.jpg"
      },
      {
        "id": 12,
        "title": "Design8",
        "category": "Design",
        "source": "Design8.png"
      },
      {
        "id": 13,
        "title": "Development1",
        "category": "Development",
        "source": "Development1.png"
      },
      {
        "id": 14,
        "title": "Development2",
        "category": "Development",
        "source": "Development2.png"
      },
      {
        "id": 15,
        "title": "Development3",
        "category": "Development",
        "source": "Development3.png"
      },
      {
        "id": 16,
        "title": "Development4",
        "category": "Development",
        "source": "Development4.jpg"
      }
    ]
  }
  